{
    "imageName": "3785.png",
    "questions": {
        "What is represented by B?": {
            "abcLabel": true,
            "answerTexts": [
                "none of the above",
                "rectum",
                "anus",
                "stomach"
            ],
            "correctAnswer": 1,
            "questionId": "3785.png-0"
        },
        "What is the bottom-most part?": {
            "abcLabel": true,
            "answerTexts": [
                "none of the above",
                "anus",
                "stomach",
                "rectum"
            ],
            "correctAnswer": 1,
            "questionId": "3785.png-2"
        },
        "Which organ is followed by the rectum?": {
            "abcLabel": false,
            "answerTexts": [
                "Small Intestine",
                "Large intestine",
                "Stomach",
                "Anus"
            ],
            "correctAnswer": 3,
            "questionId": "3785.png-1"
        }
    }
}