{
    "imageName": "4303.png",
    "questions": {
        "What is the largest planet in our solar system?": {
            "abcLabel": true,
            "answerTexts": [
                "Mars",
                "Jupiter",
                "Pluto",
                "Mercury"
            ],
            "correctAnswer": 1,
            "questionId": "4303.png-2"
        },
        "What planet is closest to the sun?": {
            "abcLabel": false,
            "answerTexts": [
                "earth",
                "none of the above",
                "mercury",
                "mars"
            ],
            "correctAnswer": 2,
            "questionId": "4303.png-0"
        },
        "Which planet is known for having rings?": {
            "abcLabel": true,
            "answerTexts": [
                "Saturn",
                "Venus",
                "Neptune",
                "Earth"
            ],
            "correctAnswer": 0,
            "questionId": "4303.png-1"
        }
    }
}