{
    "arrowHeads": {},
    "arrows": {
        "A0": {
            "id": "A0",
            "polygon": [
                [
                    247,
                    296
                ],
                [
                    147,
                    375
                ],
                [
                    97,
                    452
                ],
                [
                    151,
                    462
                ],
                [
                    206,
                    379
                ],
                [
                    261,
                    350
                ],
                [
                    244,
                    297
                ]
            ]
        },
        "A1": {
            "id": "A1",
            "polygon": [
                [
                    85,
                    647
                ],
                [
                    109,
                    725
                ],
                [
                    157,
                    792
                ],
                [
                    178,
                    811
                ],
                [
                    200,
                    780
                ],
                [
                    156,
                    731
                ],
                [
                    136,
                    687
                ],
                [
                    122,
                    653
                ],
                [
                    82,
                    646
                ]
            ]
        },
        "A2": {
            "id": "A2",
            "polygon": [
                [
                    418,
                    853
                ],
                [
                    501,
                    834
                ],
                [
                    564,
                    795
                ],
                [
                    623,
                    722
                ],
                [
                    670,
                    736
                ],
                [
                    597,
                    818
                ],
                [
                    518,
                    866
                ],
                [
                    413,
                    893
                ],
                [
                    420,
                    850
                ]
            ]
        },
        "A3": {
            "id": "A3",
            "polygon": [
                [
                    519,
                    337
                ],
                [
                    571,
                    374
                ],
                [
                    613,
                    425
                ],
                [
                    641,
                    475
                ],
                [
                    682,
                    475
                ],
                [
                    647,
                    404
                ],
                [
                    579,
                    333
                ],
                [
                    531,
                    297
                ],
                [
                    520,
                    342
                ]
            ]
        }
    },
    "blobs": {
        "B0": {
            "id": "B0",
            "polygon": [
                [
                    706,
                    713
                ],
                [
                    654,
                    715
                ],
                [
                    616,
                    675
                ],
                [
                    572,
                    647
                ],
                [
                    536,
                    640
                ],
                [
                    491,
                    634
                ],
                [
                    435,
                    577
                ],
                [
                    426,
                    549
                ],
                [
                    428,
                    527
                ],
                [
                    448,
                    497
                ],
                [
                    478,
                    491
                ],
                [
                    500,
                    487
                ],
                [
                    510,
                    461
                ],
                [
                    532,
                    452
                ],
                [
                    541,
                    473
                ],
                [
                    520,
                    491
                ],
                [
                    510,
                    509
                ],
                [
                    510,
                    532
                ],
                [
                    536,
                    524
                ],
                [
                    559,
                    530
                ],
                [
                    574,
                    550
                ],
                [
                    585,
                    526
                ],
                [
                    618,
                    505
                ],
                [
                    636,
                    485
                ],
                [
                    646,
                    489
                ],
                [
                    688,
                    484
                ],
                [
                    706,
                    495
                ],
                [
                    697,
                    520
                ],
                [
                    674,
                    538
                ],
                [
                    707,
                    525
                ],
                [
                    730,
                    509
                ],
                [
                    738,
                    518
                ],
                [
                    723,
                    549
                ],
                [
                    669,
                    574
                ],
                [
                    680,
                    592
                ],
                [
                    695,
                    620
                ],
                [
                    757,
                    638
                ],
                [
                    712,
                    713
                ],
                [
                    718,
                    710
                ],
                [
                    710,
                    712
                ]
            ]
        },
        "B1": {
            "id": "B1",
            "polygon": [
                [
                    301,
                    412
                ],
                [
                    368,
                    341
                ],
                [
                    382,
                    356
                ],
                [
                    400,
                    369
                ],
                [
                    449,
                    382
                ],
                [
                    473,
                    397
                ],
                [
                    516,
                    427
                ],
                [
                    507,
                    382
                ],
                [
                    518,
                    315
                ],
                [
                    464,
                    263
                ],
                [
                    393,
                    226
                ],
                [
                    329,
                    222
                ],
                [
                    294,
                    241
                ],
                [
                    259,
                    276
                ],
                [
                    255,
                    312
                ],
                [
                    268,
                    355
                ],
                [
                    285,
                    344
                ],
                [
                    311,
                    352
                ],
                [
                    303,
                    382
                ],
                [
                    278,
                    394
                ],
                [
                    297,
                    418
                ],
                [
                    302,
                    416
                ]
            ]
        },
        "B2": {
            "id": "B2",
            "polygon": [
                [
                    34,
                    544
                ],
                [
                    71,
                    533
                ],
                [
                    104,
                    494
                ],
                [
                    116,
                    458
                ],
                [
                    145,
                    459
                ],
                [
                    172,
                    510
                ],
                [
                    198,
                    533
                ],
                [
                    180,
                    579
                ],
                [
                    142,
                    612
                ],
                [
                    101,
                    637
                ],
                [
                    81,
                    602
                ],
                [
                    31,
                    547
                ]
            ]
        },
        "B3": {
            "id": "B3",
            "polygon": [
                [
                    322,
                    952
                ],
                [
                    375,
                    993
                ],
                [
                    397,
                    983
                ],
                [
                    419,
                    938
                ],
                [
                    362,
                    735
                ],
                [
                    355,
                    699
                ],
                [
                    384,
                    669
                ],
                [
                    401,
                    631
                ],
                [
                    371,
                    632
                ],
                [
                    337,
                    655
                ],
                [
                    345,
                    616
                ],
                [
                    320,
                    610
                ],
                [
                    306,
                    643
                ],
                [
                    290,
                    657
                ],
                [
                    262,
                    622
                ],
                [
                    235,
                    622
                ],
                [
                    249,
                    648
                ],
                [
                    248,
                    670
                ],
                [
                    212,
                    632
                ],
                [
                    189,
                    646
                ],
                [
                    211,
                    671
                ],
                [
                    237,
                    692
                ],
                [
                    244,
                    722
                ],
                [
                    197,
                    794
                ],
                [
                    172,
                    910
                ],
                [
                    188,
                    965
                ],
                [
                    211,
                    987
                ],
                [
                    239,
                    986
                ],
                [
                    271,
                    950
                ],
                [
                    279,
                    966
                ],
                [
                    303,
                    968
                ],
                [
                    317,
                    953
                ],
                [
                    325,
                    954
                ]
            ]
        }
    },
    "containers": {},
    "imageConsts": {
        "I0": {
            "id": "I0"
        }
    },
    "meaningfulSpaces": {},
    "relationships": {
        "B0+A2+B3": {
            "category": "interObjectLinkage",
            "connector": "A2",
            "destination": "B3",
            "hasDirectionality": false,
            "id": "B0+A2+B3",
            "origin": "B0"
        },
        "B1+A3+B0": {
            "category": "interObjectLinkage",
            "connector": "A3",
            "destination": "B0",
            "hasDirectionality": false,
            "id": "B1+A3+B0",
            "origin": "B1"
        },
        "B2+A0+B1": {
            "category": "interObjectLinkage",
            "connector": "A0",
            "destination": "B1",
            "hasDirectionality": false,
            "id": "B2+A0+B1",
            "origin": "B2"
        },
        "B3+A1+B2": {
            "category": "interObjectLinkage",
            "connector": "A1",
            "destination": "B2",
            "hasDirectionality": false,
            "id": "B3+A1+B2",
            "origin": "B3"
        },
        "T0+I0": {
            "category": "misc",
            "destination": "I0",
            "hasDirectionality": false,
            "id": "T0+I0",
            "origin": "T0"
        },
        "T1+I0": {
            "category": "imageTitle",
            "destination": "I0",
            "hasDirectionality": false,
            "id": "T1+I0",
            "origin": "T1"
        },
        "T2+B1": {
            "category": "intraObjectLabel",
            "destination": "B1",
            "hasDirectionality": false,
            "id": "T2+B1",
            "origin": "T2"
        },
        "T3+B2": {
            "category": "intraObjectLabel",
            "destination": "B2",
            "hasDirectionality": false,
            "id": "T3+B2",
            "origin": "T3"
        },
        "T4+B3": {
            "category": "intraObjectLabel",
            "destination": "B3",
            "hasDirectionality": false,
            "id": "T4+B3",
            "origin": "T4"
        },
        "T5+B0": {
            "category": "intraObjectLabel",
            "destination": "B0",
            "hasDirectionality": false,
            "id": "T5+B0",
            "origin": "T5"
        }
    },
    "text": {
        "T0": {
            "id": "T0",
            "rectangle": [
                [
                    649,
                    950
                ],
                [
                    748,
                    1005
                ]
            ],
            "replacementText": "B",
            "value": "point the world SUPER COLORING"
        },
        "T1": {
            "id": "T1",
            "rectangle": [
                [
                    71,
                    64
                ],
                [
                    708,
                    140
                ]
            ],
            "replacementText": "D",
            "value": "Life Cycle of a Cicada"
        },
        "T2": {
            "id": "T2",
            "rectangle": [
                [
                    353,
                    387
                ],
                [
                    452,
                    421
                ]
            ],
            "replacementText": "A",
            "value": "Nymph"
        },
        "T3": {
            "id": "T3",
            "rectangle": [
                [
                    170,
                    484
                ],
                [
                    238,
                    519
                ]
            ],
            "replacementText": "C",
            "value": "Eggs"
        },
        "T4": {
            "id": "T4",
            "rectangle": [
                [
                    376,
                    721
                ],
                [
                    449,
                    749
                ]
            ],
            "replacementText": "E",
            "value": "Adult"
        },
        "T5": {
            "id": "T5",
            "rectangle": [
                [
                    509,
                    669
                ],
                [
                    573,
                    697
                ]
            ],
            "replacementText": "F",
            "value": "Molt"
        }
    }
}