{
    "arrowHeads": {
        "H0": {
            "id": "H0",
            "orientation": 180.0,
            "rectangle": [
                [
                    208,
                    213
                ],
                [
                    219,
                    224
                ]
            ]
        },
        "H1": {
            "id": "H1",
            "orientation": 180.0,
            "rectangle": [
                [
                    217,
                    16
                ],
                [
                    227,
                    26
                ]
            ]
        },
        "H2": {
            "id": "H2",
            "orientation": 180.0,
            "rectangle": [
                [
                    217,
                    252
                ],
                [
                    226,
                    261
                ]
            ]
        },
        "H3": {
            "id": "H3",
            "orientation": 180.0,
            "rectangle": [
                [
                    160,
                    167
                ],
                [
                    171,
                    178
                ]
            ]
        },
        "H4": {
            "id": "H4",
            "orientation": 180.0,
            "rectangle": [
                [
                    245,
                    231
                ],
                [
                    252,
                    238
                ]
            ]
        },
        "H5": {
            "id": "H5",
            "orientation": 180.0,
            "rectangle": [
                [
                    113,
                    194
                ],
                [
                    123,
                    204
                ]
            ]
        },
        "H6": {
            "id": "H6",
            "orientation": 180.0,
            "rectangle": [
                [
                    213,
                    103
                ],
                [
                    221,
                    111
                ]
            ]
        },
        "H7": {
            "id": "H7",
            "orientation": 180.0,
            "rectangle": [
                [
                    158,
                    142
                ],
                [
                    167,
                    151
                ]
            ]
        },
        "H8": {
            "id": "H8",
            "orientation": 180.0,
            "rectangle": [
                [
                    161,
                    181
                ],
                [
                    172,
                    192
                ]
            ]
        },
        "H9": {
            "id": "H9",
            "orientation": 180.0,
            "rectangle": [
                [
                    167,
                    81
                ],
                [
                    177,
                    91
                ]
            ]
        }
    },
    "arrows": {
        "A0": {
            "id": "A0",
            "polygon": [
                [
                    212,
                    16
                ],
                [
                    214,
                    27
                ],
                [
                    287,
                    26
                ],
                [
                    288,
                    20
                ],
                [
                    210,
                    14
                ]
            ]
        },
        "A1": {
            "id": "A1",
            "polygon": [
                [
                    155,
                    52
                ],
                [
                    153,
                    67
                ],
                [
                    288,
                    63
                ],
                [
                    292,
                    55
                ],
                [
                    152,
                    54
                ]
            ]
        },
        "A10": {
            "id": "A10",
            "polygon": [
                [
                    246,
                    231
                ],
                [
                    244,
                    242
                ],
                [
                    292,
                    242
                ],
                [
                    292,
                    230
                ],
                [
                    244,
                    229
                ]
            ]
        },
        "A11": {
            "id": "A11",
            "polygon": [
                [
                    216,
                    250
                ],
                [
                    215,
                    260
                ],
                [
                    289,
                    261
                ],
                [
                    291,
                    254
                ],
                [
                    214,
                    249
                ]
            ]
        },
        "A12": {
            "id": "A12",
            "polygon": [
                [
                    100,
                    271
                ],
                [
                    102,
                    283
                ],
                [
                    291,
                    280
                ],
                [
                    293,
                    270
                ],
                [
                    100,
                    267
                ]
            ]
        },
        "A13": {
            "id": "A13",
            "polygon": [
                [
                    304,
                    145
                ],
                [
                    304,
                    199
                ],
                [
                    323,
                    199
                ],
                [
                    320,
                    132
                ],
                [
                    303,
                    134
                ],
                [
                    303,
                    149
                ]
            ]
        },
        "A2": {
            "id": "A2",
            "polygon": [
                [
                    165,
                    81
                ],
                [
                    166,
                    93
                ],
                [
                    291,
                    94
                ],
                [
                    284,
                    82
                ],
                [
                    167,
                    82
                ]
            ]
        },
        "A3": {
            "id": "A3",
            "polygon": [
                [
                    210,
                    105
                ],
                [
                    211,
                    114
                ],
                [
                    289,
                    112
                ],
                [
                    290,
                    101
                ],
                [
                    212,
                    104
                ]
            ]
        },
        "A4": {
            "id": "A4",
            "polygon": [
                [
                    169,
                    122
                ],
                [
                    175,
                    130
                ],
                [
                    292,
                    131
                ],
                [
                    292,
                    120
                ],
                [
                    170,
                    119
                ]
            ]
        },
        "A5": {
            "id": "A5",
            "polygon": [
                [
                    158,
                    143
                ],
                [
                    158,
                    154
                ],
                [
                    288,
                    153
                ],
                [
                    291,
                    140
                ],
                [
                    154,
                    144
                ]
            ]
        },
        "A6": {
            "id": "A6",
            "polygon": [
                [
                    159,
                    166
                ],
                [
                    161,
                    175
                ],
                [
                    289,
                    178
                ],
                [
                    293,
                    169
                ],
                [
                    159,
                    166
                ]
            ]
        },
        "A7": {
            "id": "A7",
            "polygon": [
                [
                    159,
                    180
                ],
                [
                    161,
                    192
                ],
                [
                    291,
                    191
                ],
                [
                    291,
                    182
                ],
                [
                    161,
                    181
                ]
            ]
        },
        "A8": {
            "id": "A8",
            "polygon": [
                [
                    114,
                    195
                ],
                [
                    116,
                    205
                ],
                [
                    292,
                    205
                ],
                [
                    292,
                    196
                ],
                [
                    113,
                    195
                ]
            ]
        },
        "A9": {
            "id": "A9",
            "polygon": [
                [
                    208,
                    215
                ],
                [
                    208,
                    224
                ],
                [
                    292,
                    224
                ],
                [
                    291,
                    214
                ],
                [
                    206,
                    214
                ]
            ]
        }
    },
    "blobs": {
        "B0": {
            "id": "B0",
            "polygon": [
                [
                    225,
                    17
                ],
                [
                    253,
                    45
                ],
                [
                    267,
                    77
                ],
                [
                    276,
                    108
                ],
                [
                    279,
                    138
                ],
                [
                    281,
                    192
                ],
                [
                    277,
                    230
                ],
                [
                    274,
                    263
                ],
                [
                    266,
                    286
                ],
                [
                    256,
                    301
                ],
                [
                    236,
                    316
                ],
                [
                    168,
                    331
                ],
                [
                    148,
                    331
                ],
                [
                    129,
                    331
                ],
                [
                    121,
                    331
                ],
                [
                    106,
                    331
                ],
                [
                    77,
                    325
                ],
                [
                    47,
                    313
                ],
                [
                    31,
                    288
                ],
                [
                    16,
                    244
                ],
                [
                    9,
                    194
                ],
                [
                    3,
                    128
                ],
                [
                    6,
                    91
                ],
                [
                    19,
                    56
                ],
                [
                    50,
                    25
                ],
                [
                    90,
                    9
                ],
                [
                    130,
                    0
                ],
                [
                    155,
                    0
                ],
                [
                    188,
                    3
                ],
                [
                    225,
                    18
                ]
            ]
        }
    },
    "containers": {},
    "imageConsts": {
        "I0": {
            "id": "I0"
        }
    },
    "meaningfulSpaces": {},
    "relationships": {
        "A0+H1": {
            "category": "arrowHeadTail",
            "destination": "H1",
            "hasDirectionality": false,
            "id": "A0+H1",
            "origin": "A0"
        },
        "A10+H4": {
            "category": "arrowHeadTail",
            "destination": "H4",
            "hasDirectionality": false,
            "id": "A10+H4",
            "origin": "A10"
        },
        "A11+H2": {
            "category": "arrowHeadTail",
            "destination": "H2",
            "hasDirectionality": false,
            "id": "A11+H2",
            "origin": "A11"
        },
        "A2+H9": {
            "category": "arrowHeadTail",
            "destination": "H9",
            "hasDirectionality": false,
            "id": "A2+H9",
            "origin": "A2"
        },
        "A3+H6": {
            "category": "arrowHeadTail",
            "destination": "H6",
            "hasDirectionality": false,
            "id": "A3+H6",
            "origin": "A3"
        },
        "A5+H7": {
            "category": "arrowHeadTail",
            "destination": "H7",
            "hasDirectionality": false,
            "id": "A5+H7",
            "origin": "A5"
        },
        "A6+H3": {
            "category": "arrowHeadTail",
            "destination": "H3",
            "hasDirectionality": false,
            "id": "A6+H3",
            "origin": "A6"
        },
        "A7+H8": {
            "category": "arrowHeadTail",
            "destination": "H8",
            "hasDirectionality": false,
            "id": "A7+H8",
            "origin": "A7"
        },
        "A8+H5": {
            "category": "arrowHeadTail",
            "destination": "H5",
            "hasDirectionality": false,
            "id": "A8+H5",
            "origin": "A8"
        },
        "A9+H0": {
            "category": "arrowHeadTail",
            "destination": "H0",
            "hasDirectionality": false,
            "id": "A9+H0",
            "origin": "A9"
        },
        "T0+A10+B0": {
            "category": "intraObjectLinkage",
            "connector": "A10",
            "destination": "B0",
            "hasDirectionality": false,
            "id": "T0+A10+B0",
            "origin": "T0"
        },
        "T1+A8+B0": {
            "category": "intraObjectLinkage",
            "connector": "A8",
            "destination": "B0",
            "hasDirectionality": false,
            "id": "T1+A8+B0",
            "origin": "T1"
        },
        "T10+A2+B0": {
            "category": "intraObjectLinkage",
            "connector": "A2",
            "destination": "B0",
            "hasDirectionality": false,
            "id": "T10+A2+B0",
            "origin": "T10"
        },
        "T11+A3+B0": {
            "category": "intraObjectLinkage",
            "connector": "A3",
            "destination": "B0",
            "hasDirectionality": false,
            "id": "T11+A3+B0",
            "origin": "T11"
        },
        "T12+A4+B0": {
            "category": "intraObjectLinkage",
            "connector": "A4",
            "destination": "B0",
            "hasDirectionality": false,
            "id": "T12+A4+B0",
            "origin": "T12"
        },
        "T13+A13+B0": {
            "category": "intraObjectLinkage",
            "connector": "A13",
            "destination": "B0",
            "hasDirectionality": false,
            "id": "T13+A13+B0",
            "origin": "T13"
        },
        "T2+A7+B0": {
            "category": "intraObjectLinkage",
            "connector": "A7",
            "destination": "B0",
            "hasDirectionality": false,
            "id": "T2+A7+B0",
            "origin": "T2"
        },
        "T3+A9+B0": {
            "category": "intraObjectLinkage",
            "connector": "A9",
            "destination": "B0",
            "hasDirectionality": false,
            "id": "T3+A9+B0",
            "origin": "T3"
        },
        "T4+A5+B0": {
            "category": "intraObjectLinkage",
            "connector": "A5",
            "destination": "B0",
            "hasDirectionality": false,
            "id": "T4+A5+B0",
            "origin": "T4"
        },
        "T5+A6+B0": {
            "category": "intraObjectLinkage",
            "connector": "A6",
            "destination": "B0",
            "hasDirectionality": false,
            "id": "T5+A6+B0",
            "origin": "T5"
        },
        "T6+A11+B0": {
            "category": "intraObjectLinkage",
            "connector": "A11",
            "destination": "B0",
            "hasDirectionality": false,
            "id": "T6+A11+B0",
            "origin": "T6"
        },
        "T7+A12+B0": {
            "category": "intraObjectLinkage",
            "connector": "A12",
            "destination": "B0",
            "hasDirectionality": false,
            "id": "T7+A12+B0",
            "origin": "T7"
        },
        "T8+A0+B0": {
            "category": "intraObjectLinkage",
            "connector": "A0",
            "destination": "B0",
            "hasDirectionality": false,
            "id": "T8+A0+B0",
            "origin": "T8"
        },
        "T9+A1+B0": {
            "category": "intraObjectLinkage",
            "connector": "A1",
            "destination": "B0",
            "hasDirectionality": false,
            "id": "T9+A1+B0",
            "origin": "T9"
        }
    },
    "text": {
        "T0": {
            "id": "T0",
            "rectangle": [
                [
                    292,
                    227
                ],
                [
                    307,
                    241
                ]
            ],
            "replacementText": "F",
            "value": "12"
        },
        "T1": {
            "id": "T1",
            "rectangle": [
                [
                    292,
                    193
                ],
                [
                    308,
                    209
                ]
            ],
            "replacementText": "H",
            "value": "10"
        },
        "T10": {
            "id": "T10",
            "rectangle": [
                [
                    289,
                    77
                ],
                [
                    301,
                    93
                ]
            ],
            "replacementText": "G",
            "value": "3"
        },
        "T11": {
            "id": "T11",
            "rectangle": [
                [
                    291,
                    101
                ],
                [
                    302,
                    114
                ]
            ],
            "replacementText": "K",
            "value": "4"
        },
        "T12": {
            "id": "T12",
            "rectangle": [
                [
                    291,
                    116
                ],
                [
                    302,
                    131
                ]
            ],
            "replacementText": "E",
            "value": "5"
        },
        "T13": {
            "id": "T13",
            "rectangle": [
                [
                    322,
                    156
                ],
                [
                    331,
                    179
                ]
            ],
            "replacementText": "A",
            "value": "9"
        },
        "T2": {
            "id": "T2",
            "rectangle": [
                [
                    291,
                    179
                ],
                [
                    303,
                    192
                ]
            ],
            "replacementText": "L",
            "value": "8"
        },
        "T3": {
            "id": "T3",
            "rectangle": [
                [
                    290,
                    211
                ],
                [
                    306,
                    225
                ]
            ],
            "replacementText": "J",
            "value": "11"
        },
        "T4": {
            "id": "T4",
            "rectangle": [
                [
                    289,
                    139
                ],
                [
                    300,
                    155
                ]
            ],
            "replacementText": "M",
            "value": "6"
        },
        "T5": {
            "id": "T5",
            "rectangle": [
                [
                    290,
                    160
                ],
                [
                    300,
                    177
                ]
            ],
            "replacementText": "N",
            "value": "7"
        },
        "T6": {
            "id": "T6",
            "rectangle": [
                [
                    290,
                    247
                ],
                [
                    307,
                    263
                ]
            ],
            "replacementText": "I",
            "value": "13"
        },
        "T7": {
            "id": "T7",
            "rectangle": [
                [
                    290,
                    266
                ],
                [
                    308,
                    282
                ]
            ],
            "replacementText": "D",
            "value": "14"
        },
        "T8": {
            "id": "T8",
            "rectangle": [
                [
                    285,
                    14
                ],
                [
                    297,
                    29
                ]
            ],
            "replacementText": "B",
            "value": "1"
        },
        "T9": {
            "id": "T9",
            "rectangle": [
                [
                    288,
                    47
                ],
                [
                    303,
                    65
                ]
            ],
            "replacementText": "C",
            "value": "2"
        }
    }
}